auto_git/__init__.py
auto_git/cli.py
auto_git_tool-1.2.1.dist-info/METADATA
auto_git_tool-1.2.1.dist-info/WHEEL
auto_git_tool-1.2.1.dist-info/entry_points.txt
auto_git_tool-1.2.1.dist-info/top_level.txt
auto_git_tool-1.2.1.dist-info/RECORD
