Metadata-Version: 2.4
Name: auto-git-tool
Version: 1.2.1
Summary: Git uchun avtomatlashtirilgan add, AI commit va push buyrug‘i
Home-page: https://github.com/Husanjonazamov/auto-git
Author: Husanjon Azamov
Author-email: Husanboy Azamov <azamovhusanboy08@gmail.com>
License: MIT
Project-URL: Homepage, https://github.com/Husanjonazamov/auto-git
Project-URL: Repository, https://github.com/Husanjonazamov/auto-git
Requires-Python: >=3.7
Dynamic: author
Dynamic: home-page
